floataddingpackage/__init__.py
floataddingpackage/add.py
fardin_addtwo-0.1.0.dist-info/METADATA
fardin_addtwo-0.1.0.dist-info/WHEEL
fardin_addtwo-0.1.0.dist-info/top_level.txt
fardin_addtwo-0.1.0.dist-info/RECORD
